sumy/__init__.py
sumy/__main__.py
sumy/_compat.py
sumy/utils.py
sumy/data/stopwords/arabic.txt
sumy/data/stopwords/chinese.txt
sumy/data/stopwords/czech.txt
sumy/data/stopwords/english.txt
sumy/data/stopwords/french.txt
sumy/data/stopwords/german.txt
sumy/data/stopwords/greek.txt
sumy/data/stopwords/hebrew.txt
sumy/data/stopwords/italian.txt
sumy/data/stopwords/japanese.txt
sumy/data/stopwords/korean.txt
sumy/data/stopwords/portuguese.txt
sumy/data/stopwords/slovak.txt
sumy/data/stopwords/spanish.txt
sumy/data/stopwords/ukrainian.txt
sumy/evaluation/__init__.py
sumy/evaluation/__main__.py
sumy/evaluation/content_based.py
sumy/evaluation/coselection.py
sumy/evaluation/rouge.py
sumy/models/__init__.py
sumy/models/tf.py
sumy/models/dom/__init__.py
sumy/models/dom/_document.py
sumy/models/dom/_paragraph.py
sumy/models/dom/_sentence.py
sumy/nlp/__init__.py
sumy/nlp/tokenizers.py
sumy/nlp/stemmers/__init__.py
sumy/nlp/stemmers/czech.py
sumy/nlp/stemmers/greek.py
sumy/nlp/stemmers/ukrainian.py
sumy/parsers/__init__.py
sumy/parsers/html.py
sumy/parsers/parser.py
sumy/parsers/plaintext.py
sumy/summarizers/__init__.py
sumy/summarizers/_summarizer.py
sumy/summarizers/edmundson.py
sumy/summarizers/edmundson_cue.py
sumy/summarizers/edmundson_key.py
sumy/summarizers/edmundson_location.py
sumy/summarizers/edmundson_title.py
sumy/summarizers/kl.py
sumy/summarizers/lex_rank.py
sumy/summarizers/lsa.py
sumy/summarizers/luhn.py
sumy/summarizers/random.py
sumy/summarizers/reduction.py
sumy/summarizers/sum_basic.py
sumy/summarizers/text_rank.py
tests/__init__.py
tests/test_html_parser.py
tests/test_main.py
tests/test_plaintext_parser.py
tests/test_stemmers.py
tests/test_tokenizers.py
tests/utils.py
tests/test_evaluation/__init__.py
tests/test_evaluation/test_evaluation_content_based.py
tests/test_evaluation/test_evaluation_coselection.py
tests/test_evaluation/test_evaluation_rouge.py
tests/test_models/__init__.py
tests/test_models/test_dom.py
tests/test_models/test_tf.py
sumy-0.11.0.dist-info/LICENSE.md
sumy-0.11.0.dist-info/METADATA
sumy-0.11.0.dist-info/WHEEL
sumy-0.11.0.dist-info/entry_points.txt
sumy-0.11.0.dist-info/top_level.txt
sumy-0.11.0.dist-info/RECORD
