Metadata-Version: 2.1
Name: sumy
Version: 0.11.0
Summary: Module for automatic summarization of text documents and HTML pages.
Home-page: https://github.com/miso-belica/sumy
Author: Mišo Belica
Author-email: miso.belica@gmail.com
License: Apache License, Version 2.0
Keywords: data mining,automatic summarization,data reduction,web-data extraction,NLP,natural language processing,latent semantic analysis,LSA,TextRank,LexRank
Classifier: Development Status :: 4 - Beta
Classifier: Intended Audience :: Developers
Classifier: Intended Audience :: Education
Classifier: License :: OSI Approved :: Apache Software License
Classifier: Natural Language :: Chinese (Simplified)
Classifier: Natural Language :: Czech
Classifier: Natural Language :: English
Classifier: Natural Language :: French
Classifier: Natural Language :: German
Classifier: Natural Language :: Hebrew
Classifier: Natural Language :: Italian
Classifier: Natural Language :: Japanese
Classifier: Natural Language :: Portuguese
Classifier: Natural Language :: Slovak
Classifier: Natural Language :: Spanish
Classifier: Natural Language :: Ukrainian
Classifier: Natural Language :: Greek
Classifier: Natural Language :: Arabic
Classifier: Topic :: Education
Classifier: Topic :: Internet
Classifier: Topic :: Scientific/Engineering :: Information Analysis
Classifier: Topic :: Text Processing :: Filters
Classifier: Topic :: Text Processing :: Linguistic
Classifier: Topic :: Text Processing :: Markup :: HTML
Classifier: Operating System :: OS Independent
Classifier: Programming Language :: Python
Classifier: Programming Language :: Python :: 2
Classifier: Programming Language :: Python :: 2.7
Classifier: Programming Language :: Python :: 3
Classifier: Programming Language :: Python :: 3.3
Classifier: Programming Language :: Python :: 3.4
Classifier: Programming Language :: Python :: 3.5
Classifier: Programming Language :: Python :: 3.6
Classifier: Programming Language :: Python :: 3.7
Classifier: Programming Language :: Python :: 3.8
Classifier: Programming Language :: Python :: 3.9
Classifier: Programming Language :: Python :: 3.10
Classifier: Programming Language :: Python :: Implementation :: CPython
Provides-Extra: LSA
Provides-Extra: LexRank
Provides-Extra: Japanese
Provides-Extra: Chinese
Provides-Extra: Korean
Provides-Extra: Hebrew
Provides-Extra: Greek
Provides-Extra: Arabic
License-File: LICENSE.md
